<?xml version="1.0" encoding="UTF-8"?>
<databaseChangeLog
        xmlns="http://www.liquibase.org/xml/ns/dbchangelog"
        xmlns:xsi="http://www.w3.org/2001/XMLSchema-instance"
        xsi:schemaLocation="http://www.liquibase.org/xml/ns/dbchangelog
                      http://www.liquibase.org/xml/ns/dbchangelog/dbchangelog-3.8.xsd">

    <changeSet id="20" author="dmitriy_kir">
        <tagDatabase tag="insert posts"/>
    </changeSet>

    <changeSet id="21" author="dmitriy_kir">
        <insert tableName="posts">
            <column name="id" value="1"/>
            <column name="is_active" value="1"/>
            <column name="moderation_status" value="ACCEPTED"/>
            <column name="moderator_id" value="1"/>
            <column name="user_id" value="1"/>
            <column name="time" value="2021-07-13 18:06:45"/>
            <column name="title" value="Post title №1"/>
            <column name="text" value="Post text №1"/>
            <column name="view_count" value="123"/>
        </insert>

        <insert tableName="posts">
            <column name="id" value="2"/>
            <column name="is_active" value="1"/>
            <column name="moderation_status" value="ACCEPTED"/>
            <column name="moderator_id" value="1"/>
            <column name="user_id" value="1"/>
            <column name="time" value="2021-07-13 18:12:25"/>
            <column name="title" value="Post title №2"/>
            <column name="text" value="Post text №2"/>
            <column name="view_count" value="50"/>
        </insert>

        <insert tableName="posts">
            <column name="id" value="3"/>
            <column name="is_active" value="1"/>
            <column name="moderation_status" value="ACCEPTED"/>
            <column name="moderator_id" value="1"/>
            <column name="user_id" value="2"/>
            <column name="time" value="2021-07-13 18:13:45"/>
            <column name="title" value="Post title №3"/>
            <column name="text" value="Post text №3"/>
            <column name="view_count" value="90"/>
        </insert>

        <insert tableName="posts">
            <column name="id" value="4"/>
            <column name="is_active" value="0"/>
            <column name="moderation_status" value="ACCEPTED"/>
            <column name="moderator_id" value="1"/>
            <column name="user_id" value="1"/>
            <column name="time" value="2021-07-13 18:14:30"/>
            <column name="title" value="Post title №4"/>
            <column name="text" value="Post text №4"/>
            <column name="view_count" value="156"/>
        </insert>

        <insert tableName="posts">
            <column name="id" value="5"/>
            <column name="is_active" value="1"/>
            <column name="moderation_status" value="NEW"/>
            <column name="moderator_id" value="1"/>
            <column name="user_id" value="3"/>
            <column name="time" value="2021-07-13 18:15:50"/>
            <column name="title" value="Post title №5"/>
            <column name="text" value="Post text №5"/>
            <column name="view_count" value="69"/>
        </insert>

        <insert tableName="posts">
            <column name="id" value="6"/>
            <column name="is_active" value="1"/>
            <column name="moderation_status" value="ACCEPTED"/>
            <column name="moderator_id" value="1"/>
            <column name="user_id" value="2"/>
            <column name="time" value="2021-07-13 18:16:40"/>
            <column name="title" value="Post title №6"/>
            <column name="text" value="Post text №6"/>
            <column name="view_count" value="48"/>
        </insert>

        <insert tableName="posts">
            <column name="id" value="7"/>
            <column name="is_active" value="1"/>
            <column name="moderation_status" value="ACCEPTED"/>
            <column name="moderator_id" value="1"/>
            <column name="user_id" value="1"/>
            <column name="time" value="2021-07-13 18:17:20"/>
            <column name="title" value="Post title №7"/>
            <column name="text" value="Post text №7"/>
            <column name="view_count" value="230"/>
        </insert>

        <insert tableName="posts">
            <column name="id" value="8"/>
            <column name="is_active" value="1"/>
            <column name="moderation_status" value="ACCEPTED"/>
            <column name="moderator_id" value="1"/>
            <column name="user_id" value="1"/>
            <column name="time" value="2021-07-13 18:18:40"/>
            <column name="title" value="Post title №8"/>
            <column name="text" value="Post text №8"/>
            <column name="view_count" value="47"/>
        </insert>

        <insert tableName="posts">
            <column name="id" value="9"/>
            <column name="is_active" value="1"/>
            <column name="moderation_status" value="ACCEPTED"/>
            <column name="moderator_id" value="1"/>
            <column name="user_id" value="3"/>
            <column name="time" value="2021-07-13 18:19:38"/>
            <column name="title" value="Post title №9"/>
            <column name="text" value="Post text №9"/>
            <column name="view_count" value="74"/>
        </insert>

        <insert tableName="posts">
            <column name="id" value="10"/>
            <column name="is_active" value="1"/>
            <column name="moderation_status" value="ACCEPTED"/>
            <column name="moderator_id" value="1"/>
            <column name="user_id" value="2"/>
            <column name="time" value="2021-07-13 18:20:20"/>
            <column name="title" value="Post title №10"/>
            <column name="text" value="Post text №10"/>
            <column name="view_count" value="333"/>
        </insert>

        <insert tableName="posts">
            <column name="id" value="11"/>
            <column name="is_active" value="1"/>
            <column name="moderation_status" value="ACCEPTED"/>
            <column name="moderator_id" value="1"/>
            <column name="user_id" value="1"/>
            <column name="time" value="2021-07-13 18:21:25"/>
            <column name="title" value="Post title №11"/>
            <column name="text" value="Post text №11"/>
            <column name="view_count" value="159"/>
        </insert>

        <insert tableName="posts">
            <column name="id" value="12"/>
            <column name="is_active" value="1"/>
            <column name="moderation_status" value="ACCEPTED"/>
            <column name="moderator_id" value="1"/>
            <column name="user_id" value="3"/>
            <column name="time" value="2021-07-13 18:22:23"/>
            <column name="title" value="Post title №12"/>
            <column name="text" value="Post text №12"/>
            <column name="view_count" value="78"/>
        </insert>

        <insert tableName="posts">
            <column name="id" value="13"/>
            <column name="is_active" value="1"/>
            <column name="moderation_status" value="ACCEPTED"/>
            <column name="moderator_id" value="1"/>
            <column name="user_id" value="1"/>
            <column name="time" value="2021-07-13 18:22:57"/>
            <column name="title" value="Post title №13"/>
            <column name="text" value="Post text №13"/>
            <column name="view_count" value="290"/>
        </insert>
    </changeSet>
</databaseChangeLog>